magical_sqlserver/__init__.py
magical_sqlserver/api.py
magical_sqlserver/decorators.py
magical_sqlserver-0.4.0.dist-info/LICENSE
magical_sqlserver-0.4.0.dist-info/METADATA
magical_sqlserver-0.4.0.dist-info/WHEEL
magical_sqlserver-0.4.0.dist-info/top_level.txt
magical_sqlserver-0.4.0.dist-info/RECORD
