Metadata-Version: 2.1
Name: magical-sqlserver
Version: 0.4.0
Summary: Microsoft SQL Server for applications, like magic
Home-page: https://github.com/brennoflavio/magical-sqlserver
Author: Brenno Flavio de Almeida
Author-email: brenno.flavio412@gmail.com
License: UNKNOWN
Platform: UNKNOWN
Classifier: Programming Language :: Python :: 3
Classifier: License :: OSI Approved :: MIT License
Classifier: Operating System :: OS Independent
Requires-Dist: pymssql
